main.py
FractalLibrary/__init__.py
FractalLibrary/cli.py
FractalLibrary/core/FractalLibrary.py
FractalLibrary/core/__init__.py
FractalLibrary/core/demonstrate_library.py
FractalLibrary/entities/EntityCluster.py
FractalLibrary/entities/__init__.py
FractalLibrary/patterns/__init__.py
FractalLibrary/patterns/pattern_mathematics.py
cesaret-0.1.3.dist-info/licenses/LICENSE
echonexus/__init__.py
echonexus/ai/__init__.py
echonexus/ai/character_embodiment.py
echonexus/ai/execution_monitor.py
echonexus/ai/recursive_adaptation.py
echonexus/api/__init__.py
echonexus/api/main.py
echonexus/api/state_store.py
echonexus/api/routes/__init__.py
echonexus/api/routes/feedback.py
echonexus/api/routes/state.py
echonexus/logging/__init__.py
echonexus/logging/recursive_trace_logger.py
echonexus/models/__init__.py
echonexus/models/narrative_state.py
echonexus/utils/__init__.py
echonexus/utils/async_queue.py
echonexus/utils/diff_tracker.py
echonexus/utils/redis_client.py
echonexus/utils/terminal_ledger.py
cesaret-0.1.3.dist-info/METADATA
cesaret-0.1.3.dist-info/WHEEL
cesaret-0.1.3.dist-info/entry_points.txt
cesaret-0.1.3.dist-info/top_level.txt
cesaret-0.1.3.dist-info/RECORD
