Metadata-Version: 2.4
Name: cesaret
Version: 0.1.3
Summary: CeSaReT Toolkit
Author: Codex
Requires-Python: >=3.10
License-File: LICENSE
Requires-Dist: fastapi
Requires-Dist: uvicorn
Requires-Dist: requests
Requires-Dist: redis
Requires-Dist: numpy
Dynamic: license-file
